.coveragerc
.flake8
AUTHORS
ChangeLog
Dockerfile
LICENSE
MANIFEST.in
README.md
codecov.yml
nose.cfg
requirements-dev.txt
requirements-test.txt
requirements.txt
setup.cfg
setup.py
tox.ini
.circleci/config.yml
bin/analyze
bin/coverage
bin/deploy
bin/install
bin/lint
bin/readme
bin/tag
bin/test
ssr/__init__.py
ssr/auth.py
ssr/clients.py
ssr/exceptions.py
ssr/random.py
ssr/sessions.py
ssr/utils.py
ssr.egg-info/PKG-INFO
ssr.egg-info/SOURCES.txt
ssr.egg-info/dependency_links.txt
ssr.egg-info/not-zip-safe
ssr.egg-info/pbr.json
ssr.egg-info/requires.txt
ssr.egg-info/top_level.txt
tests/__init__.py
tests/test_auth.py
tests/test_clients.py
tests/test_sessions.py
tests/test_utils.py