Metadata-Version: 2.1
Name: ssr
Version: 0.1.1
Summary: Shared-Secret Requests: A simple HTTP authentication library using shared secrets.
Home-page: https://github.com/hangarunderground/ssr
Author: Anthony Almarza
Author-email: anthony.almarza@gmail.com
License: MIT
Keywords: auth,authentication,requests,shared secrets
Platform: UNKNOWN
Classifier: Development Status :: 4 - Beta
Classifier: Environment :: Console
Classifier: Intended Audience :: Developers
Classifier: Intended Audience :: Information Technology
Classifier: License :: OSI Approved :: MIT License
Classifier: Operating System :: OS Independent
Classifier: Programming Language :: Python
